{"noiseKey":{"private":{"type":"Buffer","data":"QAAxXE9M7tQ0/rwtBiV5NGD0G30N/MqcHlT6B6JgxnI="},"public":{"type":"Buffer","data":"Ru/iTvWRjzpe2keS91p+uYv2iTq/4hjF9HmcDcXD5XA="}},"pairingEphemeralKeyPair":{"private":{"type":"Buffer","data":"SE06etSdVwqNvw+wj2v4wmA7Yxvl9df/DWSzCEH0A1k="},"public":{"type":"Buffer","data":"8QV5kTaPU1/8yuBcw54b+7Z6qni0kR2c6Z992ZQUbQY="}},"signedIdentityKey":{"private":{"type":"Buffer","data":"uMmKF0VYUP7BYjc0rhuEGI7qmiNR+aYhdTek8Atma2o="},"public":{"type":"Buffer","data":"PL/AsVNwkg0Om6fB/ddNXaD/iMQVL3n32gLwO/zMy2A="}},"signedPreKey":{"keyPair":{"private":{"type":"Buffer","data":"UFAvBmJVqkt5PbsLgrBM9G+iPvH0YDgARWnXm2x8Ink="},"public":{"type":"Buffer","data":"znBOYOaxZLjGPcRS374RrV5xzORENlTCYBZTmKEpnyI="}},"signature":{"type":"Buffer","data":"AfXSu/qIQNBx+R41AGoqBeQVwbP/YT0384ZHSe+D+XcZyk1aa9O4RIq3l570msJwWuD7hgDvyYUI5yThK6C4jg=="},"keyId":1},"registrationId":14,"advSecretKey":"VSkRXYf4mb6e6g1dwzQXhULPQeCFsYFsKu96Qg/pRU4=","processedHistoryMessages":[{"key":{"remoteJid":"233505874809@s.whatsapp.net","fromMe":true,"id":"8C7D7E651A2BD04FB45168225F0EACF8"},"messageTimestamp":1757304145},{"key":{"remoteJid":"233505874809@s.whatsapp.net","fromMe":true,"id":"85DEA724AF5AD25995ED77FBA738AAC0"},"messageTimestamp":1757304160},{"key":{"remoteJid":"233505874809@s.whatsapp.net","fromMe":true,"id":"C571573B50644F64632DB021B454F939"},"messageTimestamp":1757304187},{"key":{"remoteJid":"233505874809@s.whatsapp.net","fromMe":true,"id":"2E60F8182F2AE8C33A0592B2D9AB2440"},"messageTimestamp":1757304214},{"key":{"remoteJid":"233505874809@s.whatsapp.net","fromMe":true,"id":"AF997B11362158F5431B64DD6CD2052D"},"messageTimestamp":1757304237},{"key":{"remoteJid":"233505874809@s.whatsapp.net","fromMe":true,"id":"19CAAD7FAD1A75F9B229C49A4944A56E"},"messageTimestamp":1757304259},{"key":{"remoteJid":"233505874809@s.whatsapp.net","fromMe":true,"id":"1FD979EA3B7C29E3FB6A262838E4A16A"},"messageTimestamp":1757304280},{"key":{"remoteJid":"233505874809@s.whatsapp.net","fromMe":true,"id":"4E852EDDFCB6B05C6A699FDEC159301C"},"messageTimestamp":1757304301},{"key":{"remoteJid":"233505874809@s.whatsapp.net","fromMe":true,"id":"7EEAAD0262AB25E3126E7E99679670E6"},"messageTimestamp":1757304325},{"key":{"remoteJid":"233505874809@s.whatsapp.net","fromMe":true,"id":"CCC0960FD13A75CADF5C0C75F965F6E1"},"messageTimestamp":1757304348},{"key":{"remoteJid":"233505874809@s.whatsapp.net","fromMe":true,"id":"9126838DAE4F27D82651935EA03FCA76"},"messageTimestamp":1757304367},{"key":{"remoteJid":"233505874809@s.whatsapp.net","fromMe":true,"id":"9562423A62666B373DBEE14B37F19278"},"messageTimestamp":1757304387},{"key":{"remoteJid":"233505874809@s.whatsapp.net","fromMe":true,"id":"8F996349CE38AB46EC917964F0937F2B"},"messageTimestamp":1757304406},{"key":{"remoteJid":"233505874809@s.whatsapp.net","fromMe":true,"id":"7BEE2D63930A9F3CBFA0E107CB7378F9"},"messageTimestamp":1757304430},{"key":{"remoteJid":"233505874809@s.whatsapp.net","fromMe":true,"id":"321DB12F7C9998FB9E5E42C93B52B6A6"},"messageTimestamp":1757304447},{"key":{"remoteJid":"233505874809@s.whatsapp.net","fromMe":true,"id":"9200FDBE6F1E57763EBE3BA9DAEAE3A5"},"messageTimestamp":1757304460}],"nextPreKeyId":133,"firstUnuploadedPreKeyId":133,"accountSyncCounter":1,"accountSettings":{"unarchiveChats":false},"deviceId":"J0-dzjrZQCCLEImlspuI2w","phoneId":"6dfbd0b0-096d-4ad5-87a0-6adf4b1cb2b8","identityId":{"type":"Buffer","data":"5JtrltZHnWk7Yxi7EqdefirlqBE="},"registered":true,"backupToken":{"type":"Buffer","data":"yMNKnzr1URRMcrR7Ufu3o9jmD7g="},"registration":{},"pairingCode":"TZCE3EGE","me":{"id":"233505874809:44@s.whatsapp.net","name":"𓄂 𝙂𝙐𝙔 𓃲","lid":"204239234191612:44@lid"},"account":{"details":"CN6KvpoGEL2q+cUGGAIgACgA","accountSignatureKey":"8blXKjRtkef4HLSI2r7Ugb/Y62N+QP21RO6EVee+9G0=","accountSignature":"Z6kaHv/ns0u7I+UVQ1nVsO8swvm5BI2hlxgaPhFVcAL42jXyTmvKy3lFc2Spi6ZYNcl61U2USzWK4Hii2sSvBA==","deviceSignature":"bSR9MYGVBWW5e4e3tbPAI7/MTeH3SKMbCm8shKQsrY7bnWxF2HPD8RioVfQEUoj8Nz/p+JsssNbBeUnL7nWZig=="},"signalIdentities":[{"identifier":{"name":"233505874809:44@s.whatsapp.net","deviceId":0},"identifierKey":{"type":"Buffer","data":"BfG5Vyo0bZHn+By0iNq+1IG/2OtjfkD9tUTuhFXnvvRt"}}],"platform":"smba","routingInfo":{"type":"Buffer","data":"CAUIDQ=="},"lastAccountSyncTimestamp":1757304139,"lastPropHash":"3gPUJk","myAppStateKeyId":"AAAAAFto"}